MANIFEST.in
README.rst
setup.cfg
setup.py
versioneer.py
dfttk/EVcheck_QHA.py
dfttk/__init__.py
dfttk/_version.py
dfttk/custodian_jobs.py
dfttk/espei_compat.py
dfttk/ftasks.py
dfttk/fworks.py
dfttk/input_sets.py
dfttk/pyEVfind.py
dfttk/pyphon.py
dfttk/pythelec.py
dfttk/pythfind.py
dfttk/run_task_ext.py
dfttk/utils.py
dfttk/vasprun_fix.py
dfttk/wflows.py
dfttk.egg-info/PKG-INFO
dfttk.egg-info/SOURCES.txt
dfttk.egg-info/dependency_links.txt
dfttk.egg-info/entry_points.txt
dfttk.egg-info/requires.txt
dfttk.egg-info/top_level.txt
dfttk/analysis/__init__.py
dfttk/analysis/debye.py
dfttk/analysis/formation_energies.py
dfttk/analysis/phonon.py
dfttk/analysis/quasiharmonic.py
dfttk/analysis/relaxing.py
dfttk/analysis/thermal_electronic.py
dfttk/analysis/ywplot.py
dfttk/analysis/ywutils.py
dfttk/analysis/database/__init__.py
dfttk/elasticity/__init__.py
dfttk/elasticity/elastic.py
dfttk/elasticity/parse_outputs.py
dfttk/scripts/QHAAnalysis_renew.py
dfttk/scripts/__init__.py
dfttk/scripts/assign_fworker_name.py
dfttk/scripts/config_dfttk.py
dfttk/scripts/mongodb_user.py
dfttk/scripts/querydb.py
dfttk/scripts/run_dfttk.py
dfttk/scripts/run_dfttk_ext.py
dfttk/structure_builders/__init__.py
dfttk/structure_builders/aflow_prototype_db.json
dfttk/structure_builders/dilute.py
dfttk/structure_builders/parse_anrl_prototype.py
dfttk/structure_builders/prl_structure.py
dfttk/structure_builders/prototype_anrl.all
dfttk/structure_builders/protoype.py
dfttk/structure_builders/sqs.py
dfttk/structure_builders/sqs_db.py
dfttk/structure_builders/substitutions.py