Metadata-Version: 2.1
Name: dfttk
Version: 0.3.4
Summary: Density functional theory workflows for finite temperature thermodynamics based on atomate workflows. Created by the Phases Research Lab
Home-page: https://github.com/phasesresearchlab/dfttk
Author: Brandon Bocklund
Author-email: brandonbocklund@gmail.com
License: MIT
Platform: UNKNOWN
Classifier: Development Status :: 3 - Alpha
Classifier: Intended Audience :: Science/Research
Classifier: Topic :: Scientific/Engineering :: Physics
Classifier: Topic :: Scientific/Engineering :: Chemistry
Classifier: License :: OSI Approved :: MIT License
Classifier: Programming Language :: Python :: 3
Classifier: Programming Language :: Python :: 3.6
Classifier: Programming Language :: Python :: 3.7
Classifier: Programming Language :: Python :: 3.8
Provides-Extra: dev
